{"code":1,"msg":"获取成功","data":{"homeworkId":"qty1aaisbbnpajrqd2revg","uniqueId":"fn3hakmsk6pfwisvwpvnpa","paperStructUnique":"","courseOpenId":"ppvnatisl55lkxnq3ztcq","openClassId":"fftwatisilzhua9vnp8lvg","homeworkTitle":"第一章  绪论","ztWay":2,"paperType":1,"homeworkType":1,"totalScore":100.00,"state":2,"remark":"","questions":[{"paperStuQuestionId":"fn3hakmsk6pfwisvwpvnpa_0_4","questionId":"0dmuaaisgorocnifmgtg","questionType":1,"queTypeName":"单选题","sortOrder":0,"orderBy":0,"title":"<p><strong>现代医学模式为</strong></p><p><br/></p>","dataJson":"[{\"SortOrder\":0,\"Content\":\"生物医学模式\",\"IsAnswer\":false},{\"SortOrder\":1,\"Content\":\"自然科学医学模式\",\"IsAnswer\":false},{\"SortOrder\":2,\"Content\":\"生物-心理医学模式\",\"IsAnswer\":false},{\"SortOrder\":3,\"Content\":\"生物-心理-社会医学模式&nbsp;\",\"IsAnswer\":true},{\"SortOrder\":4,\"Content\":\"生物-生理-社会医学模式\",\"IsAnswer\":false}]","answer":"3","resultAnalysis":"","questionScore":5.00,"isAssignmented":1,"studentAnswer":"3","isRight":1,"getScore":5.00,"bigQuestionId":"","commentary":"","commentaryFileData":[],"subQuestionList":[]},{"paperStuQuestionId":"fn3hakmsk6pfwisvwpvnpa_0_5","questionId":"0oevaais2qjaoccyemyfxq","questionType":1,"queTypeName":"单选题","sortOrder":1,"orderBy":1,"title":"<p><strong>小刘是病人严某的责任护士，小刘为严某制订了详细的护理计划并实施护理措施，小刘不在岗时，由其他护士按她的计划实施护理。小刘对病人严某实施的是</strong></p><p><br/></p>","dataJson":"[{\"SortOrder\":0,\"Content\":\"个案护理\",\"IsAnswer\":false},{\"SortOrder\":1,\"Content\":\"功能制护理\",\"IsAnswer\":false},{\"SortOrder\":2,\"Content\":\"小组制护理&nbsp;\",\"IsAnswer\":false},{\"SortOrder\":3,\"Content\":\"责任制护理\",\"IsAnswer\":true},{\"SortOrder\":4,\"Content\":\"综合护理\",\"IsAnswer\":false}]","answer":"3","resultAnalysis":"","questionScore":5.00,"isAssignmented":1,"studentAnswer":"3","isRight":1,"getScore":5.00,"bigQuestionId":"","commentary":"","commentaryFileData":[],"subQuestionList":[]},{"paperStuQuestionId":"fn3hakmsk6pfwisvwpvnpa_0_14","questionId":"aomwaaisuzfg1sormnd2w","questionType":1,"queTypeName":"单选题","sortOrder":2,"orderBy":2,"title":"<p>现阶段新型冠状病毒流行，某社区医疗点为了更好地预防该传染病，让社区护士利用知-信-行模式，使社区居民掌握到新型冠状病毒的知识，转变观念，采取相应的防护措施，取得了一定的成效。<strong>此项护理工作内容属于</strong></p><p><br/></p>","dataJson":"[{\"SortOrder\":0,\"Content\":\"临床护理\",\"IsAnswer\":false},{\"SortOrder\":1,\"Content\":\"社区护理&nbsp;\",\"IsAnswer\":true},{\"SortOrder\":2,\"Content\":\"护理教育&nbsp;\",\"IsAnswer\":false},{\"SortOrder\":3,\"Content\":\"护理管理\",\"IsAnswer\":false},{\"SortOrder\":4,\"Content\":\"护理科研\",\"IsAnswer\":false}]","answer":"1","resultAnalysis":"","questionScore":5.00,"isAssignmented":1,"studentAnswer":"1","isRight":1,"getScore":5.00,"bigQuestionId":"","commentary":"","commentaryFileData":[],"subQuestionList":[]},{"paperStuQuestionId":"fn3hakmsk6pfwisvwpvnpa_0_8","questionId":"g20uaais3pjko48ptdqqkg","questionType":1,"queTypeName":"单选题","sortOrder":3,"orderBy":3,"title":"<p><strong>世界上第一所护士学校创办于</strong></p><p><br/></p>","dataJson":"[{\"SortOrder\":0,\"Content\":\"1820年英国\",\"IsAnswer\":false},{\"SortOrder\":1,\"Content\":\"1860年英国\",\"IsAnswer\":true},{\"SortOrder\":2,\"Content\":\"1820年法国\",\"IsAnswer\":false},{\"SortOrder\":3,\"Content\":\"1860年法国\",\"IsAnswer\":false},{\"SortOrder\":4,\"Content\":\"1888年英国\",\"IsAnswer\":false}]","answer":"1","resultAnalysis":"","questionScore":5.00,"isAssignmented":1,"studentAnswer":"1","isRight":1,"getScore":5.00,"bigQuestionId":"","commentary":"","commentaryFileData":[],"subQuestionList":[]},{"paperStuQuestionId":"fn3hakmsk6pfwisvwpvnpa_0_15","questionId":"ljovaaisyjdoe0hxjxmeba","questionType":1,"queTypeName":"单选题","sortOrder":4,"orderBy":4,"title":"<p><strong>护理理论四个基本概念的核心是</strong></p><p><br/></p>","dataJson":"[{\"SortOrder\":0,\"Content\":\"环境\",\"IsAnswer\":false},{\"SortOrder\":1,\"Content\":\"护理\",\"IsAnswer\":false},{\"SortOrder\":2,\"Content\":\"疾病\",\"IsAnswer\":false},{\"SortOrder\":3,\"Content\":\"健康&nbsp;&nbsp;\",\"IsAnswer\":false},{\"SortOrder\":4,\"Content\":\"人\",\"IsAnswer\":true}]","answer":"4","resultAnalysis":"","questionScore":5.00,"isAssignmented":1,"studentAnswer":"4","isRight":1,"getScore":5.00,"bigQuestionId":"","commentary":"","commentaryFileData":[],"subQuestionList":[]},{"paperStuQuestionId":"fn3hakmsk6pfwisvwpvnpa_0_12","questionId":"mhwvaaisi5jhwbl5lpq4w","questionType":1,"queTypeName":"单选题","sortOrder":5,"orderBy":5,"title":"<p><strong>中医“三分治、七分养”中的“养”是指</strong></p><p><br/></p>","dataJson":"[{\"SortOrder\":0,\"Content\":\"护理&nbsp;\",\"IsAnswer\":true},{\"SortOrder\":1,\"Content\":\"医疗\",\"IsAnswer\":false},{\"SortOrder\":2,\"Content\":\"食疗\",\"IsAnswer\":false},{\"SortOrder\":3,\"Content\":\"药疗\",\"IsAnswer\":false},{\"SortOrder\":4,\"Content\":\"中医\",\"IsAnswer\":false}]","answer":"0","resultAnalysis":"","questionScore":5.00,"isAssignmented":1,"studentAnswer":"0","isRight":1,"getScore":5.00,"bigQuestionId":"","commentary":"","commentaryFileData":[],"subQuestionList":[]},{"paperStuQuestionId":"fn3hakmsk6pfwisvwpvnpa_0_0","questionId":"vj0waaisbibi8ud31qdwg","questionType":1,"queTypeName":"单选题","sortOrder":6,"orderBy":6,"title":"<p><strong>现代护理学的变化和发展经历的三个阶段是</strong></p><p><br/></p>","dataJson":"[{\"SortOrder\":0,\"Content\":\"以疾病、病人、人的健康为中心的护理阶段&nbsp;\",\"IsAnswer\":true},{\"SortOrder\":1,\"Content\":\"以疾病、人的健康、病人为中心的护理阶段\",\"IsAnswer\":false},{\"SortOrder\":2,\"Content\":\"以病人、疾病、人的健康为中心的护理阶段\",\"IsAnswer\":false},{\"SortOrder\":3,\"Content\":\"以人的健康、疾病、病人为中心的护理阶段\",\"IsAnswer\":false},{\"SortOrder\":4,\"Content\":\"以人的健康、病人、疾病为中心的护理阶段\",\"IsAnswer\":false}]","answer":"0","resultAnalysis":"","questionScore":5.00,"isAssignmented":1,"studentAnswer":"0","isRight":1,"getScore":5.00,"bigQuestionId":"","commentary":"","commentaryFileData":[],"subQuestionList":[]},{"paperStuQuestionId":"fn3hakmsk6pfwisvwpvnpa_0_6","questionId":"w5ywaaisfojl0q0ew6ovqa","questionType":1,"queTypeName":"单选题","sortOrder":7,"orderBy":7,"title":"<p><strong>以疾病为中心的护理阶段，护理的特点不正确的是</strong></p><p><br/></p>","dataJson":"[{\"SortOrder\":0,\"Content\":\"护理从属于医疗，护士被看做医生的助手\",\"IsAnswer\":false},{\"SortOrder\":1,\"Content\":\"护理工作的内容是执行医嘱和各项护理技术操作&nbsp;&nbsp;\",\"IsAnswer\":false},{\"SortOrder\":2,\"Content\":\"在实践中形成了一套较为规范的护理技术常规&nbsp;\",\"IsAnswer\":false},{\"SortOrder\":3,\"Content\":\"应用护理程序的工作方法对病人实施整体护理\",\"IsAnswer\":true},{\"SortOrder\":4,\"Content\":\"只注重局部病症，而不重视对人的全面照顾\",\"IsAnswer\":false}]","answer":"3","resultAnalysis":"","questionScore":5.00,"isAssignmented":1,"studentAnswer":"3","isRight":1,"getScore":5.00,"bigQuestionId":"","commentary":"","commentaryFileData":[],"subQuestionList":[]},{"paperStuQuestionId":"fn3hakmsk6pfwisvwpvnpa_0_2","questionId":"yl0vaaisbfnhjidlwxsmq","questionType":1,"queTypeName":"单选题","sortOrder":8,"orderBy":8,"title":"<p><strong>我国举行首次护士执业考试的时间是</strong></p><p><br/></p>","dataJson":"[{\"SortOrder\":0,\"Content\":\"1950年\",\"IsAnswer\":false},{\"SortOrder\":1,\"Content\":\"1979年\",\"IsAnswer\":false},{\"SortOrder\":2,\"Content\":\"1993年\",\"IsAnswer\":false},{\"SortOrder\":3,\"Content\":\"1995年\",\"IsAnswer\":true},{\"SortOrder\":4,\"Content\":\"1998年\",\"IsAnswer\":false}]","answer":"3","resultAnalysis":"","questionScore":5.00,"isAssignmented":1,"studentAnswer":"3","isRight":1,"getScore":5.00,"bigQuestionId":"","commentary":"","commentaryFileData":[],"subQuestionList":[]},{"paperStuQuestionId":"fn3hakmsk6pfwisvwpvnpa_12_9","questionId":"kwhwazgsd7nakksoz6kp2q","questionType":1,"queTypeName":"单选题","sortOrder":9,"orderBy":9,"title":"<p><span style=\"font-size: 10.5pt; font-family: 新宋体;\">在护理学中有关“健康”这一概念的描述，正确的是</span></p>","dataJson":"[{\"SortOrder\":0,\"Content\":\"健康就是没有疾病或不适\",\"IsAnswer\":false},{\"SortOrder\":1,\"Content\":\"健康和疾病具有清晰的界限\",\"IsAnswer\":false},{\"SortOrder\":2,\"Content\":\"健康是一个动态、连续的过程\",\"IsAnswer\":true},{\"SortOrder\":3,\"Content\":\"人的健康观念受单独某一因素的影响\",\"IsAnswer\":false}]","answer":"2","resultAnalysis":"","questionScore":5.00,"isAssignmented":1,"studentAnswer":"2","isRight":1,"getScore":5.00,"bigQuestionId":"","commentary":"","commentaryFileData":[],"subQuestionList":[]},{"paperStuQuestionId":"fn3hakmsk6pfwisvwpvnpa_13_3","questionId":"kwhwazgsgr5dqwtatkqjeg","questionType":1,"queTypeName":"单选题","sortOrder":10,"orderBy":10,"title":"<p><span style=\"font-size: 10.5pt; font-family: 新宋体;\">在护理学中有关“人”这一概念的描述，不正确的是</span></p>","dataJson":"[{\"SortOrder\":0,\"Content\":\"人是一个开放的系统\",\"IsAnswer\":false},{\"SortOrder\":1,\"Content\":\"人是护理实践的核心和基础\",\"IsAnswer\":false},{\"SortOrder\":2,\"Content\":\"人是由生理、心理、社会等多方面组成的整体\",\"IsAnswer\":false},{\"SortOrder\":3,\"Content\":\"人在不同发展阶段人都有相同的基本需要\",\"IsAnswer\":true}]","answer":"3","resultAnalysis":"","questionScore":5.00,"isAssignmented":1,"studentAnswer":"3","isRight":1,"getScore":5.00,"bigQuestionId":"","commentary":"","commentaryFileData":[],"subQuestionList":[]},{"paperStuQuestionId":"fn3hakmsk6pfwisvwpvnpa_17_10","questionId":"kwhwazgso7tizeopas1tgg","questionType":1,"queTypeName":"单选题","sortOrder":11,"orderBy":11,"title":"<p><span style=\"font-size: 10.5pt; font-family: 新宋体;\">以分组的方式对病人进行全面护理的工作方法为</span></p>","dataJson":"[{\"SortOrder\":0,\"Content\":\"个案护理\",\"IsAnswer\":false},{\"SortOrder\":1,\"Content\":\"功能制护理\",\"IsAnswer\":false},{\"SortOrder\":2,\"Content\":\"小组制护理\",\"IsAnswer\":true},{\"SortOrder\":3,\"Content\":\"责任制护理\",\"IsAnswer\":false}]","answer":"2","resultAnalysis":"","questionScore":5.00,"isAssignmented":1,"studentAnswer":"2","isRight":1,"getScore":5.00,"bigQuestionId":"","commentary":"","commentaryFileData":[],"subQuestionList":[]},{"paperStuQuestionId":"fn3hakmsk6pfwisvwpvnpa_18_1","questionId":"kwhwazgslbnk4hxrexdymw","questionType":1,"queTypeName":"单选题","sortOrder":12,"orderBy":12,"title":"<p><span style=\"font-size: 10.5pt; font-family: 新宋体;\">“以病人为中心”的护理阶段的特点不包括</span></p>","dataJson":"[{\"SortOrder\":0,\"Content\":\"护士与医生是合作伙伴\",\"IsAnswer\":false},{\"SortOrder\":1,\"Content\":\"运用护理程序的工作方法\",\"IsAnswer\":false},{\"SortOrder\":2,\"Content\":\"对病人提供整体护理\",\"IsAnswer\":false},{\"SortOrder\":3,\"Content\":\"护士是医生的助手\",\"IsAnswer\":true}]","answer":"3","resultAnalysis":"","questionScore":5.00,"isAssignmented":1,"studentAnswer":"3","isRight":1,"getScore":5.00,"bigQuestionId":"","commentary":"","commentaryFileData":[],"subQuestionList":[]},{"paperStuQuestionId":"fn3hakmsk6pfwisvwpvnpa_20_13","questionId":"kwhwazgs959bm7qv76gyw","questionType":1,"queTypeName":"单选题","sortOrder":13,"orderBy":13,"title":"<p><span style=\"font-size: 10.5pt; font-family: 新宋体;\">功能制护理的优点不包括</span></p>","dataJson":"[{\"SortOrder\":0,\"Content\":\"节省人力\",\"IsAnswer\":false},{\"SortOrder\":1,\"Content\":\"任务单一\",\"IsAnswer\":false},{\"SortOrder\":2,\"Content\":\"易于管理\",\"IsAnswer\":false},{\"SortOrder\":3,\"Content\":\"能主动与病人沟通\",\"IsAnswer\":true}]","answer":"3","resultAnalysis":"","questionScore":5.00,"isAssignmented":1,"studentAnswer":"3","isRight":1,"getScore":5.00,"bigQuestionId":"","commentary":"","commentaryFileData":[],"subQuestionList":[]},{"paperStuQuestionId":"fn3hakmsk6pfwisvwpvnpa_0_7","questionId":"gii0aaisujfabzwkemeaka","questionType":4,"queTypeName":"填空题(客观)","sortOrder":14,"orderBy":14,"title":"<p>护理学的任务包括&nbsp;&nbsp;&nbsp;　&nbsp;　 、&nbsp;&nbsp;&nbsp;　&nbsp;　 、&nbsp;&nbsp;&nbsp;　&nbsp;　 、&nbsp;&nbsp;&nbsp;　　&nbsp;&nbsp;&nbsp;四个方面。</p><p><br/></p><p><img class=\"questionIndex\" data-index=\"1\" src=\"https://zjy2.icve.com.cn/common/images/question_button/BlankSpace1.gif\"/></p><p><img class=\"questionIndex\" data-index=\"2\" src=\"https://zjy2.icve.com.cn/common/images/question_button/BlankSpace2.gif\"/></p><p><img class=\"questionIndex\" data-index=\"3\" src=\"https://zjy2.icve.com.cn/common/images/question_button/BlankSpace3.gif\"/></p><p><img class=\"questionIndex\" data-index=\"4\" src=\"https://zjy2.icve.com.cn/common/images/question_button/BlankSpace4.gif\"/></p>","dataJson":"[{\"SortOrder\":0,\"Content\":\"促进健康\",\"CaseSensitive\":false,\"IsAnswer\":true,\"AlternativeAnswer\":[]},{\"SortOrder\":1,\"Content\":\"预防疾病\",\"CaseSensitive\":false,\"IsAnswer\":true,\"AlternativeAnswer\":[]},{\"SortOrder\":2,\"Content\":\"恢复健康\",\"CaseSensitive\":false,\"IsAnswer\":true,\"AlternativeAnswer\":[]},{\"SortOrder\":3,\"Content\":\"减轻痛苦\",\"CaseSensitive\":false,\"IsAnswer\":true,\"AlternativeAnswer\":[]}]","answer":"[{\"SortOrder\":0,\"Content\":\"促进健康\",\"CaseSensitive\":false,\"IsAnswer\":true,\"AlternativeAnswer\":[]},{\"SortOrder\":1,\"Content\":\"预防疾病\",\"CaseSensitive\":false,\"IsAnswer\":true,\"AlternativeAnswer\":[]},{\"SortOrder\":2,\"Content\":\"恢复健康\",\"CaseSensitive\":false,\"IsAnswer\":true,\"AlternativeAnswer\":[]},{\"SortOrder\":3,\"Content\":\"减轻痛苦\",\"CaseSensitive\":false,\"IsAnswer\":true,\"AlternativeAnswer\":[]}]","resultAnalysis":"","questionScore":20.00,"isAssignmented":1,"studentAnswer":"[{\"SortOrder\":0,\"Content\":\"促进健康\"},{\"SortOrder\":1,\"Content\":\"预防疾病\"},{\"SortOrder\":2,\"Content\":\"恢复健康\"},{\"SortOrder\":3,\"Content\":\"减轻痛苦\"}]","isRight":1,"getScore":20.00,"bigQuestionId":"","commentary":"","commentaryFileData":[],"subQuestionList":[]},{"paperStuQuestionId":"fn3hakmsk6pfwisvwpvnpa_0_11","questionId":"oh41aais2k1p4rfpcrl91g","questionType":4,"queTypeName":"填空题(客观)","sortOrder":15,"orderBy":15,"title":"<p>临床护理的内容包括（&nbsp; &nbsp; &nbsp; &nbsp;）和&nbsp; （&nbsp; &nbsp; &nbsp; &nbsp;）&nbsp;。<br/><img class=\"questionIndex\" data-index=\"1\" src=\"https://zjy2.icve.com.cn/common/images/question_button/BlankSpace1.gif\"/><img class=\"questionIndex\" data-index=\"2\" src=\"https://zjy2.icve.com.cn/common/images/question_button/BlankSpace2.gif\"/></p>","dataJson":"[{\"SortOrder\":0,\"Content\":\"基础护理\",\"CaseSensitive\":false,\"IsAnswer\":true,\"AlternativeAnswer\":[]},{\"SortOrder\":1,\"Content\":\"专科护理\",\"CaseSensitive\":false,\"IsAnswer\":true,\"AlternativeAnswer\":[]}]","answer":"[{\"SortOrder\":0,\"Content\":\"基础护理\",\"CaseSensitive\":false,\"IsAnswer\":true,\"AlternativeAnswer\":[]},{\"SortOrder\":1,\"Content\":\"专科护理\",\"CaseSensitive\":false,\"IsAnswer\":true,\"AlternativeAnswer\":[]}]","resultAnalysis":"","questionScore":10.00,"isAssignmented":1,"studentAnswer":"[{\"SortOrder\":0,\"Content\":\"基础护理\"},{\"SortOrder\":1,\"Content\":\"专科护理\"}]","isRight":1,"getScore":10.00,"bigQuestionId":"","commentary":"","commentaryFileData":[],"subQuestionList":[]}],"isNeedSyncRecord":false,"isShowAnswer":1}}